simplebot_echo.py
simplebot_echo-1.1.0.dist-info/LICENSE
simplebot_echo-1.1.0.dist-info/METADATA
simplebot_echo-1.1.0.dist-info/WHEEL
simplebot_echo-1.1.0.dist-info/entry_points.txt
simplebot_echo-1.1.0.dist-info/top_level.txt
simplebot_echo-1.1.0.dist-info/RECORD
