Metadata-Version: 2.1
Name: simplebot-echo
Version: 1.1.0
Summary: An example plugin for SimpleBot, a Delta Chat(http://delta.chat/) bot
Home-page: https://github.com/simplebot-org/simplebot_echo
Author: The SimpleBot Contributors
Author-email: adbenitez@nauta.cu
License: MPL
Keywords: simplebot plugin deltachat
Platform: UNKNOWN
Classifier: Development Status :: 4 - Beta
Classifier: Environment :: Plugins
Classifier: Programming Language :: Python :: 3
Classifier: License :: OSI Approved :: Mozilla Public License 2.0 (MPL 2.0)
Classifier: Operating System :: OS Independent
Classifier: Topic :: Utilities
Requires-Dist: simplebot (>=2.0.0)
Provides-Extra: dev
Requires-Dist: simplebot (>=2.0.0) ; extra == 'dev'
Requires-Dist: pytest (>=6.2.4) ; extra == 'dev'
Requires-Dist: black (>=21.7b0) ; extra == 'dev'
Requires-Dist: mypy (>=0.910) ; extra == 'dev'
Requires-Dist: isort (>=5.9.3) ; extra == 'dev'
Requires-Dist: pylint (>=2.9.6) ; extra == 'dev'
Requires-Dist: pylama (>=7.7.1) ; extra == 'dev'
Requires-Dist: types-pkg-resources (>=0.1.3) ; extra == 'dev'
Provides-Extra: test
Requires-Dist: pytest (>=6.2.4) ; extra == 'test'
